{"ts": 1782010242.2662325, "mode": "overhaul \u2014 search paused, building expert library", "cluster": {"workers": [{"id": "desktop-3080", "host": "DESKTOP-3SI71G8 (192.168.1.227)", "gpus": [{"util": 10, "mem_used": 826, "mem_total": 10240, "temp": 48}], "status": "running", "current_job": "job-1782010117-11404", "capabilities": ["gpu", "langdata", "wikidata", "codedata"], "limits": {"max_temp": 85.0, "resume_temp": 75.0, "idle_minutes": 10.0}, "eval": {"name": null}, "age": 9.0}, {"id": "laptop-5070", "host": "?", "gpus": [{"util": 100, "mem_used": 0, "mem_total": 12227, "temp": 56}], "status": "running", "current_job": "job-1782010117-11405", "capabilities": ["gpu", "vm", "langdata", "wikidata", "codedata"], "limits": {"max_temp": 85.0, "resume_temp": 75.0, "idle_minutes": 0.0}, "eval": {"name": null}, "age": 3.3}], "queued": 3242, "running": 2, "ts": 1782010238.1554222}, "library": {"experts_done": 303, "experts_total": 3546, "skills": 1770, "by_field": {"compression": {"total": 78, "done": 2}, "arithmetic": {"total": 20, "done": 20}, "arithmetic_long": {"total": 84, "done": 4}, "signal_dsp": {"total": 86, "done": 5}, "number_theory": {"total": 74, "done": 4}, "astronomy_calc": {"total": 122, "done": 7}, "physics_energy": {"total": 90, "done": 2}, "physics_motion": {"total": 80, "done": 5}, "strings_text": {"total": 56, "done": 4}, "chemistry_stoich": {"total": 84, "done": 4}, "color_rgb": {"total": 108, "done": 3}, "dates_time": {"total": 80, "done": 5}, "units_measure": {"total": 52, "done": 3}, "boolean_circuits": {"total": 106, "done": 7}, "graph_algorithms": {"total": 86, "done": 3}, "linguistics": {"total": 80, "done": 3}, "cryptography_classic": {"total": 86, "done": 6}, "sports_stats": {"total": 126, "done": 7}, "logic_puzzles": {"total": 94, "done": 5}, "matching": {"total": 20, "done": 20}, "logic_boolean": {"total": 72, "done": 5}, "probability": {"total": 62, "done": 4}, "sequences": {"total": 46, "done": 2}, "electronics": {"total": 84, "done": 3}, "pharma_dosage": {"total": 102, "done": 3}, "encoding_bases": {"total": 66, "done": 12}, "geometry_angles": {"total": 110, "done": 11}, "matrix_ops": {"total": 84, "done": 2}, "finance_money": {"total": 60, "done": 1}, "voting_ranking": {"total": 54, "done": 2}, "aggregation": {"total": 20, "done": 20}, "economics": {"total": 92, "done": 2}, "geometry": {"total": 68, "done": 1}, "navigation": {"total": 64, "done": 2}, "grammar_punct": {"total": 66, "done": 1}, "game_scoring": {"total": 110, "done": 1}, "combinatorics": {"total": 66, "done": 1}, "structure": {"total": 20, "done": 20}, "data_tables": {"total": 66, "done": 0}, "geometry_3d": {"total": 102, "done": 0}, "symbolic": {"total": 20, "done": 20}, "set_theory": {"total": 68, "done": 0}, "probability_stats": {"total": 64, "done": 0}, "string_algorithms": {"total": 42, "done": 1}, "memory": {"total": 24, "done": 24}, "statistics": {"total": 52, "done": 0}, "filter": {"total": 20, "done": 20}, "ordering": {"total": 20, "done": 20}, "music_theory": {"total": 120, "done": 0}, "recipe_scaling": {"total": 84, "done": 0}, "corpus": {"total": 6, "done": 6}}}, "core": {"trained": false, "note": "seed router built; full train pending the complete library"}}